{
    "keep": {
        "days": true,
        "amount": 14
    },
    "auditLog": "logs\\requests\\daily\\.66602cdde70fd43456e51d0c9addc83824638c4d-audit.json",
    "files": [
        {
            "date": 1676541378818,
            "name": "logs\\requests\\daily\\2023-02-16.log",
            "hash": "a21dd78899c07c1444ae273e94a26c130e354de1ec4d89e34e1af8ec98f4cec1"
        },
        {
            "date": 1676601808958,
            "name": "logs\\requests\\daily\\2023-02-17.log",
            "hash": "53ed1dc216b7f184bab753f4a7ddf7bf4540d4777a83e99c71069fe6d2087daf"
        }
    ],
    "hashType": "sha256"
}